aiokeycloak/__init__.py
aiokeycloak/authorization/__init__.py
aiokeycloak/authorization/permission.py
aiokeycloak/authorization/policy.py
aiokeycloak/authorization/role.py
aiokeycloak/exceptions.py
aiokeycloak/integrations/__init__.py
aiokeycloak/integrations/starlette/__init__.py
aiokeycloak/integrations/starlette/protected.py
aiokeycloak/integrations/starlette/store/__init__.py
aiokeycloak/integrations/starlette/store/base.py
aiokeycloak/integrations/starlette/store/bearer.py
aiokeycloak/integrations/starlette/store/cookie.py
aiokeycloak/integrations/starlette/store/session.py
aiokeycloak/openid.py
aiokeycloak/session.py
aiokeycloak/types.py
aiokeycloak/uma_permissions.py
aiokeycloak/url_patterns.py
aiokeycloak-0.0.2.dist-info/WHEEL
aiokeycloak-0.0.2.dist-info/METADATA
aiokeycloak-0.0.2.dist-info/RECORD
